app/__init__.py
app/config.py
app/main.py
app/mcp.py
app/models.py
app/services.py
app/utils0.py
app/obsidian-template/app.json
app/obsidian-template/appearance.json
app/obsidian-template/community-plugins.json
app/obsidian-template/core-plugins.json
app/obsidian-template/zk-prefixer.json
app/obsidian-template/plugins/obsidian-minimal-settings/data.json
app/obsidian-template/plugins/obsidian-minimal-settings/main.js
app/obsidian-template/plugins/obsidian-minimal-settings/manifest.json
app/obsidian-template/plugins/obsidian-style-settings/data.json
app/obsidian-template/plugins/obsidian-style-settings/main.js
app/obsidian-template/plugins/obsidian-style-settings/manifest.json
app/obsidian-template/plugins/obsidian-style-settings/styles.css
app/obsidian-template/themes/Minimal/manifest.json
app/obsidian-template/themes/Minimal/theme.css
install/__init__.py
install/group.md
install/load.md
install/report.md
install/save.md
tliner-0.4.2.dist-info/METADATA
tliner-0.4.2.dist-info/WHEEL
tliner-0.4.2.dist-info/entry_points.txt
tliner-0.4.2.dist-info/RECORD
