Metadata-Version: 2.4
Name: tliner
Version: 0.4.2
Summary: Timeliner 🌟 - AI's diary. Track AI agent work with markdown log
Author-email: "sinai.io" <r@sinai.io>
License: Proprietary
Keywords: ai-agents,fastmcp,logging,markdown,mcp,milestones
Requires-Python: >=3.11
Requires-Dist: fastmcp==2.12.2
Requires-Dist: loguru==0.7.3
Requires-Dist: pydantic==2.11.7
Requires-Dist: python-frontmatter==1.1.0
Requires-Dist: typer==0.17.4
Provides-Extra: dev
Requires-Dist: pytest-mock==3.15.0; extra == 'dev'
Requires-Dist: pytest==8.4.2; extra == 'dev'
